pycodeless/__init__.py
pycodeless/_api.py
pycodeless/_generate.py
pycodeless/_llm.py
pycodeless/_load.py
pycodeless/_openai_llm.py
pycodeless/_parse.py
pycodeless-0.2.8.dist-info/LICENSE
pycodeless-0.2.8.dist-info/METADATA
pycodeless-0.2.8.dist-info/WHEEL
pycodeless-0.2.8.dist-info/RECORD
