Metadata-Version: 2.1
Name: pycodeless
Version: 0.2.8
Summary: Build Python code using natural language as a universal interface
Home-page: https://github.com/hacksparr0w/pycodeless
License: MIT
Keywords: natural,language,codegen,programming,llm,codeless
Author: hacksparr0w
Author-email: hacksparr0w@protonmail.com
Requires-Python: >=3.8,<4.0
Classifier: License :: OSI Approved :: MIT License
Classifier: Programming Language :: Python :: 3
Classifier: Programming Language :: Python :: 3.8
Classifier: Programming Language :: Python :: 3.9
Classifier: Programming Language :: Python :: 3.10
Classifier: Programming Language :: Python :: 3.11
Requires-Dist: openai (>=0.27.4,<0.28.0)
Project-URL: Documentation, https://github.com/hacksparr0w/pycodeless
Project-URL: Repository, https://github.com/hacksparr0w/pycodeless
